{"Games": [{"player1":"Brunner, Benedikt","player2":"Zurborg, Uwe","result":"WhiteWon","gametype":"Rapid","event":"Vorschau","date":"2023-04-19"},{"player1":"Brunner, Benedikt","player2":"Petersen, Heinrich","result":"WhiteWon","gametype":"Rapid","event":"Vorschau","date":"2023-04-19"},{"player1":"Petersen, Heinrich","player2":"Brunner, Benedikt","result":"WhiteWon","gametype":"Rapid","event":"Vorschau","date":"2023-04-19"},{"player1":"Iwanicki, Marcel","player2":"Zurborg, Uwe","result":"WhiteWon","gametype":"Rapid","event":"Vorschau","date":"2023-04-19"},{"player1":"Iwanicki, Marcel","player2":"Petersen, Heinrich","result":"WhiteWon","gametype":"Rapid","event":"Vorschau","date":"2023-04-19"},{"player1":"Zurborg, Uwe","player2":"Brunner, Benedikt","result":"WhiteWon","gametype":"Rapid","event":"Vorschau","date":"2023-04-19"}]}